pyeco/__init__.py
pyeco/_bindiff.py
pyeco/_dec2hex.py
pyeco/_max_array.py
pyeco-0.5.dist-info/METADATA
pyeco-0.5.dist-info/WHEEL
pyeco-0.5.dist-info/top_level.txt
pyeco-0.5.dist-info/RECORD
