Metadata-Version: 2.1
Name: pyeco
Version: 0.5
Summary: useful python things
Home-page: UNKNOWN
Author: Nikita Kuzin
Author-email: getsense@yandex.ru
License: UNKNOWN
Platform: UNKNOWN
